avproxyrotate/LICENSE
avproxyrotate/README.MD
avproxyrotate/__init__.py
avproxyrotate/requirements.txt
avproxyrotate/thirdparty.json
avproxyrotate-0.10.dist-info/LICENSE.rst
avproxyrotate-0.10.dist-info/METADATA
avproxyrotate-0.10.dist-info/WHEEL
avproxyrotate-0.10.dist-info/top_level.txt
avproxyrotate-0.10.dist-info/RECORD
