Metadata-Version: 2.1
Name: avproxyrotate
Version: 0.10
Summary: Rotates Avast proxy servers
Home-page: https://github.com/hansalemaos/avproxyrotate
Author: Johannes Fischer
Author-email: <aulasparticularesdealemaosp@gmail.com>
License: MIT
Keywords: avast,proxy,rotate
Classifier: Development Status :: 4 - Beta
Classifier: Programming Language :: Python :: 3 :: Only
Classifier: Programming Language :: Python :: 3.9
Classifier: Topic :: Scientific/Engineering :: Visualization
Classifier: Topic :: Software Development :: Libraries :: Python Modules
Classifier: Topic :: Text Editors :: Text Processing
Classifier: Topic :: Text Processing :: General
Classifier: Topic :: Text Processing :: Indexing
Classifier: Topic :: Text Processing :: Filters
Classifier: Topic :: Utilities
License-File: LICENSE.rst
Requires-Dist: keyboard
Requires-Dist: kthread-sleep
Requires-Dist: pefile
Requires-Dist: psutil
Requires-Dist: regex
Requires-Dist: regexfilesearch
Requires-Dist: repeatdecorator
Requires-Dist: requests
